my_digital_signature/SIGNATURE.py
my_digital_signature/__init__.py
my_digital_signature/requirements.txt
my_digital_signature-0.1.1.dist-info/entry_points.txt
my_digital_signature-0.1.1.dist-info/LICENSE.txt
my_digital_signature-0.1.1.dist-info/WHEEL
my_digital_signature-0.1.1.dist-info/METADATA
my_digital_signature-0.1.1.dist-info/RECORD
