Metadata-Version: 2.1
Name: my-digital-signature
Version: 0.1.1
Summary: 
License: GPL-3.0-or-later
Author: ConstantZero
Author-email: mrzero@duck.com
Requires-Python: >=3.8,<4.0
Classifier: License :: OSI Approved :: GNU General Public License v3 or later (GPLv3+)
Classifier: Programming Language :: Python :: 3
Classifier: Programming Language :: Python :: 3.8
Classifier: Programming Language :: Python :: 3.9
Classifier: Programming Language :: Python :: 3.10
Requires-Dist: num2words (>=0.5.12,<0.6.0)
